agrifoodpy/__init__.py
agrifoodpy/array_accessor.py
agrifoodpy/food/__init__.py
agrifoodpy/food/food.py
agrifoodpy/food/model.py
agrifoodpy/food/tests/__init__.py
agrifoodpy/food/tests/test_food.py
agrifoodpy/food/tests/test_model.py
agrifoodpy/impact/__init__.py
agrifoodpy/impact/impact.py
agrifoodpy/impact/model.py
agrifoodpy/impact/tests/__init__.py
agrifoodpy/impact/tests/test_model.py
agrifoodpy/land/__init__.py
agrifoodpy/land/land.py
agrifoodpy/land/model.py
agrifoodpy/land/tests/__init__.py
agrifoodpy/land/tests/test_land.py
agrifoodpy/land/tests/test_model.py
agrifoodpy/pipeline/__init__.py
agrifoodpy/pipeline/pipeline.py
agrifoodpy/pipeline/tests/__init__.py
agrifoodpy/pipeline/tests/test_pipeline.py
agrifoodpy/population/__init__.py
agrifoodpy/population/population.py
agrifoodpy/population/tests/__init__.py
agrifoodpy/population/tests/test_population.py
agrifoodpy/tests/__init__.py
agrifoodpy/tests/test_base_class.py
agrifoodpy/utils/__init__.py
agrifoodpy/utils/dict_utils.py
agrifoodpy/utils/nodes.py
agrifoodpy/utils/scaling.py
agrifoodpy/utils/tests/__init__.py
agrifoodpy/utils/tests/test_add_items.py
agrifoodpy/utils/tests/test_add_years.py
agrifoodpy/utils/tests/test_copy_datablock.py
agrifoodpy/utils/tests/test_dict_utils.py
agrifoodpy/utils/tests/test_load_dataset.py
agrifoodpy/utils/tests/test_print_datablock.py
agrifoodpy/utils/tests/test_scaling.py
agrifoodpy/utils/tests/test_write_to_datablock.py
agrifoodpy-0.2.0.dist-info/licenses/LICENCE.rst
agrifoodpy-0.2.0.dist-info/METADATA
agrifoodpy-0.2.0.dist-info/WHEEL
agrifoodpy-0.2.0.dist-info/top_level.txt
agrifoodpy-0.2.0.dist-info/RECORD
