Metadata-Version: 2.4
Name: AgriFoodPy
Version: 0.2.0
Summary: A package for modelling food systems
Home-page: https://github.com/FixOurFood/AgriFoodPy
Author: FixOurFood developers
Author-email: juanpablo.cordero@york.ac.uk
License: BSD-3-Clause license
License-File: LICENCE.rst
Requires-Dist: numpy
Requires-Dist: pandas
Requires-Dist: xarray
Requires-Dist: matplotlib
Dynamic: author
Dynamic: author-email
Dynamic: description
Dynamic: description-content-type
Dynamic: home-page
Dynamic: license
Dynamic: license-file
Dynamic: requires-dist
Dynamic: summary
